cli/__init__.py
cli/cli.py
cli/command.py
cli/BitSrunCore/__init__.py
cli/BitSrunCore/core.py
cli/BitSrunCore/encryption/__init__.py
cli/BitSrunCore/encryption/srun_base64.py
cli/BitSrunCore/encryption/srun_md5.py
cli/BitSrunCore/encryption/srun_sha1.py
cli/BitSrunCore/encryption/srun_xencode.py
srun_bit-0.2.2.dist-info/LICENSE
srun_bit-0.2.2.dist-info/METADATA
srun_bit-0.2.2.dist-info/WHEEL
srun_bit-0.2.2.dist-info/entry_points.txt
srun_bit-0.2.2.dist-info/top_level.txt
srun_bit-0.2.2.dist-info/RECORD
