Metadata-Version: 2.1
Name: srun-bit
Version: 0.2.2
Summary: A cli to login BIT (Beijing Institute of Technology) network.
Home-page: https://github.com/fangli-li/bit-srun-cli
Author: Fang Li
License: UNKNOWN
Platform: UNKNOWN
Classifier: Programming Language :: Python :: 3
Classifier: License :: OSI Approved :: MIT License
Classifier: Operating System :: OS Independent
Requires-Dist: Click
Requires-Dist: Requests
